mqttsensor/__init__.py
mqttsensor/config.py
mqttsensor/main.py
mqttsensor/mqtt/__init__.py
mqttsensor/mqtt/client.py
mqttsensor/mqtt/message_store.py
mqttsensor-0.2.1.dist-info/METADATA
mqttsensor-0.2.1.dist-info/WHEEL
mqttsensor-0.2.1.dist-info/entry_points.txt
mqttsensor-0.2.1.dist-info/licenses/LICENSE
mqttsensor-0.2.1.dist-info/RECORD
