Metadata-Version: 2.4
Name: mqttsensor
Version: 0.2.1
Summary: A standard library for MQTT sensors within a home -> Given the topic and payload, it will create a sensor object. The payload will be inot the format expected by the [mqtt-influxdb](https://github.com/yfredrix/mqtt-influxdb) container.
Author-email: yfredrix <skier@live.nl>
License-File: LICENSE
Requires-Python: >=3.10
Requires-Dist: loguru>=0.7.3
Requires-Dist: paho-mqtt>=2.1.0
Requires-Dist: toml>=0.10.2
